{
    "$schema": "https://zed.dev/schema/themes/v0.2.0.json",
    "name": "Rust Belt",
    "author": "Dylan Reece",
    "themes": [
        {
            "name": "Rust Belt",
            "appearance": "dark",
            "style": {
                "background": "#1a1311",
                "background.appearance": "opaque",
                "border": "#3d2b23",
                "border.variant": "#2a1d17",
                "border.focused": "#ff7f3f",
                "border.selected": "#ffa161",
                "border.transparent": "#00000000",
                "border.disabled": "#1d1613",
                "elevated_surface.background": "#1d1613",
                "surface.background": "#1a1311",
                "element.background": "#2e221c",
                "element.hover": "#3d2d26",
                "element.active": "#4d3930",
                "element.selected": "#ff7f3f",
                "element.disabled": "#2e221c",
                "drop_target.background": "#ff7f3f44",
                "ghost_element.background": "#00000000",
                "ghost_element.hover": "#2e221c55",
                "ghost_element.active": "#3d2d2666",
                "ghost_element.selected": "#ff7f3f33",
                "ghost_element.disabled": "#2e221c44",
                "text": "#f5e4d7",
                "text.muted": "#c4a890",
                "text.placeholder": "#9a7d69",
                "text.disabled": "#705447",
                "text.accent": "#ff7f3f",
                "icon": "#f5e4d7",
                "icon.muted": "#c4a890",
                "icon.disabled": "#9a7d69",
                "icon.placeholder": "#9a7d69",
                "icon.accent": "#ff7f3f",
                "status_bar.background": "#1a1311",
                "title_bar.background": "#1a1311",
                "title_bar.inactive_background": "#150f0d",
                "toolbar.background": "#1a1311",
                "panel.background": "#1a1311",
                "tab_bar.background": "#1a1311",
                "tab.inactive_background": "#1d161388",
                "tab.active_background": "#1a1311",
                "editor.background": "#1a1311",
                "editor.gutter.background": "#1a1311",
                "editor.subheader.background": "#150f0d",
                "editor.active_line.background": "#2e221c33",
                "editor.highlighted_line.background": "#2e221c55",
                "editor.line_number": "#9a7d69",
                "editor.active_line_number": "#f5e4d7",
                "editor.invisible": "#705447",
                "editor.wrap_guide": "#3d2b23",
                "editor.active_wrap_guide": "#4d3930",
                "editor.indent_guide": "#3d2b23",
                "editor.indent_guide_active": "#4d3930",
                "editor.document_highlight.read_background": "#ff7f3f33",
                "editor.document_highlight.write_background": "#ff7f3f44",
                "editor.document_highlight.bracket_background": "#ffa16122",
                "link_text.hover": "#ff7f3f",
                "conflict": "#f4c430",
                "conflict.background": "#f4c43022",
                "conflict.border": "#f4c43044",
                "created": "#72d672",
                "created.background": "#72d67222",
                "created.border": "#72d67244",
                "deleted": "#d64545",
                "deleted.background": "#d6454522",
                "deleted.border": "#d6454544",
                "error": "#d64545",
                "error.background": "#d6454522",
                "error.border": "#d6454544",
                "hidden": "#9a7d69",
                "hidden.background": "#9a7d6922",
                "hidden.border": "#9a7d6944",
                "hint": "#78c6d3",
                "hint.background": "#78c6d322",
                "hint.border": "#78c6d344",
                "ignored": "#9a7d69",
                "ignored.background": "#9a7d6922",
                "ignored.border": "#9a7d6944",
                "info": "#7ca5d6",
                "info.background": "#7ca5d622",
                "info.border": "#7ca5d644",
                "modified": "#f4c430",
                "modified.background": "#f4c43022",
                "modified.border": "#f4c43044",
                "predictive": "#c4a890",
                "predictive.background": "#c4a89022",
                "predictive.border": "#c4a89044",
                "renamed": "#b98fd6",
                "renamed.background": "#b98fd622",
                "renamed.border": "#b98fd644",
                "success": "#72d672",
                "success.background": "#72d67222",
                "success.border": "#72d67244",
                "unreachable": "#9a7d69",
                "unreachable.background": "#9a7d6922",
                "unreachable.border": "#9a7d6944",
                "warning": "#ffb03b",
                "warning.background": "#ffb03b22",
                "warning.border": "#ffb03b44",
                "players": [
                    {
                        "cursor": "#ff7f3f",
                        "background": "#ff7f3f",
                        "selection": "#ff7f3f33"
                    }
                ],
                "syntax": {
                    "attribute": {
                        "color": "#f4c430"
                    },
                    "boolean": {
                        "color": "#b98fd6"
                    },
                    "comment": {
                        "color": "#9a7d69",
                        "font_style": "italic"
                    },
                    "comment.doc": {
                        "color": "#c4a890",
                        "font_style": "italic"
                    },
                    "constant": {
                        "color": "#b98fd6"
                    },
                    "constructor": {
                        "color": "#7ca5d6"
                    },
                    "embedded": {
                        "color": "#f5e4d7"
                    },
                    "emphasis": {
                        "font_style": "italic"
                    },
                    "emphasis.strong": {
                        "font_weight": 700
                    },
                    "enum": {
                        "color": "#78c6d3"
                    },
                    "function": {
                        "color": "#7ca5d6"
                    },
                    "hint": {
                        "color": "#c4a890",
                        "font_style": "italic"
                    },
                    "keyword": {
                        "color": "#ff7f3f"
                    },
                    "label": {
                        "color": "#7ca5d6"
                    },
                    "link_text": {
                        "color": "#78c6d3",
                        "font_style": "italic"
                    },
                    "link_uri": {
                        "color": "#78c6d3"
                    },
                    "number": {
                        "color": "#b98fd6"
                    },
                    "operator": {
                        "color": "#ff7f3f"
                    },
                    "predictive": {
                        "color": "#9a7d69",
                        "font_style": "italic"
                    },
                    "preproc": {
                        "color": "#f5e4d7"
                    },
                    "primary": {
                        "color": "#f5e4d7"
                    },
                    "property": {
                        "color": "#f5e4d7"
                    },
                    "punctuation": {
                        "color": "#c4a890"
                    },
                    "punctuation.bracket": {
                        "color": "#c4a890"
                    },
                    "punctuation.delimiter": {
                        "color": "#c4a890"
                    },
                    "punctuation.list_marker": {
                        "color": "#7ca5d6"
                    },
                    "punctuation.special": {
                        "color": "#ff7f3f"
                    },
                    "string": {
                        "color": "#72d672"
                    },
                    "string.escape": {
                        "color": "#b98fd6"
                    },
                    "string.regex": {
                        "color": "#f4c430"
                    },
                    "string.special": {
                        "color": "#f4c430"
                    },
                    "string.special.symbol": {
                        "color": "#f4c430"
                    },
                    "tag": {
                        "color": "#d64545"
                    },
                    "text.literal": {
                        "color": "#72d672"
                    },
                    "title": {
                        "color": "#7ca5d6",
                        "font_weight": 700
                    },
                    "type": {
                        "color": "#78c6d3"
                    },
                    "variable": {
                        "color": "#f5e4d7"
                    },
                    "variable.special": {
                        "color": "#d64545"
                    },
                    "variant": {
                        "color": "#7ca5d6"
                    }
                },
                "terminal.background": "#1a1311ff",
                "terminal.foreground": "#f5e4d7ff",
                "terminal.bright_foreground": "#f5e4d7ff",
                "terminal.dim_foreground": "#c4a890ff",
                "terminal.ansi.black": "#2e221c",
                "terminal.ansi.bright_black": "#705447",
                "terminal.ansi.dim_black": "#1a1311",
                "terminal.ansi.red": "#d64545",
                "terminal.ansi.bright_red": "#f86767",
                "terminal.ansi.dim_red": "#ab3737",
                "terminal.ansi.green": "#72d672",
                "terminal.ansi.bright_green": "#94f894",
                "terminal.ansi.dim_green": "#5bab5b",
                "terminal.ansi.yellow": "#f4c430",
                "terminal.ansi.bright_yellow": "#ffe652",
                "terminal.ansi.dim_yellow": "#c39d26",
                "terminal.ansi.blue": "#7ca5d6",
                "terminal.ansi.bright_blue": "#9ec7f8",
                "terminal.ansi.dim_blue": "#6384ab",
                "terminal.ansi.magenta": "#b98fd6",
                "terminal.ansi.bright_magenta": "#dbb1f8",
                "terminal.ansi.dim_magenta": "#9472ab",
                "terminal.ansi.cyan": "#78c6d3",
                "terminal.ansi.bright_cyan": "#9ae8f5",
                "terminal.ansi.dim_cyan": "#609ea9",
                "terminal.ansi.white": "#f5e4d7",
                "terminal.ansi.bright_white": "#fff6eb",
                "terminal.ansi.dim_white": "#c4b6ac"
            }
        }
    ]
}
